Metadata-Version: 2.1
Name: sys-detection
Version: 1.3.4
Summary: A library to detect the operating system, its version, architecture, etc.
Home-page: https://github.com/yugabyte/sys-detection
Author: Mikhail Bautin
Author-email: mbautin@users.noreply.github.com
License-File: LICENSE
Requires-Dist: autorepr
Provides-Extra: dev
Requires-Dist: codecheck; extra == "dev"
Requires-Dist: pycodestyle; extra == "dev"
Requires-Dist: mypy; extra == "dev"
Requires-Dist: pytest; extra == "dev"
Requires-Dist: twine; extra == "dev"
